{
    "sentences": [
    {
    "sentence": "My cousin Diego, born with achondroplasia (the most common form of dwarfism) to my aunt Carmen and uncle Javier in Guadalajara, Mexico in 1988, moved with his family to Los Angeles when he was 6 years old after receiving a scholarship for specialized medical treatment at Shriners Hospital, overcame relentless bullying throughout his childhood by channeling his energy into Paralympic swimming where he set three world records and won gold medals in Athens (2004), Beijing (2008), and London (2012), earned his PhD in Biomedical Engineering from Stanford at 26 where he developed revolutionary prosthetic limbs specifically designed for children with limb differences, married his college sweetheart Sophia (a pediatric occupational therapist whom he met during his hospital volunteer work) in 2015, adopted twin girls from foster care in 2019, and now heads the Adaptive Technologies Division at Boston Children's Hospital while serving as a prominent advocate for inclusive design in medical devices.",
    "extracted_information": {
        "name": "Diego",
        "relationship": "Cousin",
        "medical_condition": "Achondroplasia (most common form of dwarfism)",
        "mother_name": "Carmen",
        "mother_relationship": "Aunt",
        "father_name": "Javier",
        "father_relationship": "Uncle",
        "birth_location": "Guadalajara, Mexico",
        "birth_year": 1988,
        "relocation_age": 6,
        "relocation_destination": "Los Angeles",
        "relocation_reason": "Scholarship for specialized medical treatment",
        "treatment_location": "Shriners Hospital",
        "childhood_challenge": "Relentless bullying",
        "coping_mechanism": "Paralympic swimming",
        "athletic_achievements": "Set three world records",
        "medals": ["Gold medal in Athens 2004", "Gold medal in Beijing 2008", "Gold medal in London 2012"],
        "education": "PhD in Biomedical Engineering",
        "university": "Stanford",
        "degree_age": 26,
        "innovation": "Revolutionary prosthetic limbs for children with limb differences",
        "spouse_name": "Sophia",
        "spouse_occupation": "Pediatric occupational therapist",
        "meeting_context": "Hospital volunteer work",
        "marriage_year": 2015,
        "children": "Adopted twin girls from foster care",
        "adoption_year": 2019,
        "current_position": "Heads Adaptive Technologies Division",
        "workplace": "Boston Children's Hospital",
        "advocacy_role": "Prominent advocate for inclusive design in medical devices"
    }
    },
    {
    "sentence": "After being rescued from the rubble of her collapsed apartment building in Port-au-Prince following the devastating 2010 Haiti earthquake that claimed the lives of both her parents, my daughter Elise—who was only four years old and suffering from multiple fractures and severe dehydration when American aid workers found her 72 hours after the disaster—was airlifted to Miami Children's Hospital where my wife (then a pediatric trauma surgeon doing volunteer work with Doctors Without Borders) performed emergency surgery to save her crushed left leg, became her temporary guardian during six months of intensive rehabilitation, successfully petitioned for emergency adoption when no surviving relatives could be located despite extensive Red Cross searches, adapted to the challenges of raising a traumatized child who spoke only Haitian Creole while learning English and struggling with PTSD, and has now—thirteen years later—proudly watched Elise graduate as valedictorian of her high school class with a full scholarship to Johns Hopkins University where she plans to study Medicine with a focus on disaster relief and refugee healthcare.",
    "extracted_information": {
        "name": "Elise",
        "relationship": "Daughter",
        "disaster_type": "Earthquake",
        "disaster_location": "Port-au-Prince, Haiti",
        "disaster_year": 2010,
        "parents_status": "Both deceased in earthquake",
        "rescue_circumstance": "From rubble of collapsed apartment building",
        "rescue_timing": "72 hours after disaster",
        "age_at_rescue": 4,
        "medical_conditions": ["Multiple fractures", "Severe dehydration"],
        "rescuers": "American aid workers",
        "medical_evacuation": "Airlifted to Miami Children's Hospital",
        "wife_occupation": "Pediatric trauma surgeon",
        "wife_organization": "Doctors Without Borders",
        "medical_procedure": "Emergency surgery to save crushed left leg",
        "guardian_status": "Temporary guardian",
        "rehabilitation_duration": "Six months",
        "adoption_type": "Emergency adoption",
        "adoption_reason": "No surviving relatives located",
        "search_organization": "Red Cross",
        "parenting_challenges": ["Raising traumatized child", "Language barrier (Haitian Creole)"],
        "child_challenges": ["Learning English", "PTSD"],
        "current_timeframe": "Thirteen years later",
        "educational_achievement": "Valedictorian of high school class",
        "scholarship": "Full scholarship to Johns Hopkins University",
        "career_goal": "Medicine with focus on disaster relief and refugee healthcare"
    }
    },
    {
    "sentence": "My maternal grandmother, Mei-Ling Wong Chang, born in a small fishing village outside Shanghai in 1937, escaped Communist China with her parents via Hong Kong in 1949 aboard a dangerously overcrowded merchant vessel, spent three years in a refugee processing center in Taiwan before securing sponsorship from a Presbyterian church in Oakland, California in 1952, worked 14-hour days in her parents' laundry business while attending night school to learn English, became the first in her family to attend college when she received a partial scholarship to UC Berkeley in 1957 where she faced significant discrimination as one of only four Asian women in the Chemistry program, met my grandfather (a Chinese-American graduate student in Engineering whose family had been in California since the Gold Rush) at a cultural celebration in 1960, conducted groundbreaking research on flame retardants that led to stricter safety regulations for children's pajamas in the 1970s, raised five children including my mother while working full-time as a senior chemist at Lawrence Berkeley National Laboratory, and still makes the best dim sum in our family at age 87 using recipes she memorized from her grandmother that have never been written down.",
    "extracted_information": {
        "name": "Mei-Ling Wong Chang",
        "relationship": "Maternal grandmother",
        "birth_year": 1937,
        "birth_location": "Small fishing village outside Shanghai",
        "emigration_context": "Escaped Communist China",
        "emigration_route": "Via Hong Kong",
        "emigration_year": 1949,
        "transportation": "Dangerously overcrowded merchant vessel",
        "interim_location": "Refugee processing center in Taiwan",
        "interim_duration": "Three years",
        "immigration_sponsor": "Presbyterian church",
        "immigration_destination": "Oakland, California",
        "immigration_year": 1952,
        "work_circumstance": "14-hour days in parents' laundry business",
        "educational_pursuit": "Night school to learn English",
        "educational_milestone": "First in family to attend college",
        "scholarship": "Partial scholarship to UC Berkeley",
        "college_entry_year": 1957,
        "college_challenge": "Significant discrimination",
        "demographic_context": "One of only four Asian women in Chemistry program",
        "grandfather_meeting": 1960,
        "grandfather_background": "Chinese-American graduate student in Engineering",
        "grandfather_family_history": "Family in California since Gold Rush",
        "meeting_context": "Cultural celebration",
        "research_focus": "Groundbreaking research on flame retardants",
        "research_impact": "Stricter safety regulations for children's pajamas",
        "research_period": "1970s",
        "children_count": 5,
        "named_child": "Mother",
        "career": "Senior chemist at Lawrence Berkeley National Laboratory",
        "work_schedule": "Full-time while raising children",
        "current_age": 87,
        "culinary_skill": "Makes the best dim sum in family",
        "recipe_origin": "Memorized from her grandmother",
        "recipe_documentation": "Never been written down"
    }
    },
    {
    "sentence": "While researching my family tree for a school project in 2018, my son Benjamin stumbled upon a remarkable coincidence that neither side of our family had previously discovered: his paternal great-grandfather William Harrison (my husband's grandfather who served as a bomber pilot in the 8th Air Force during WWII) and his maternal great-grandfather Rudolf Müller (my grandfather who had been conscripted into the Luftwaffe as a fighter pilot) had actually engaged in direct aerial combat over Dresden on February 15, 1945, as documented in their respective military records and flight logs, with William's B-17 sustaining damage from Rudolf's Messerschmitt before both men returned safely to their bases, only to meet 60 years later at Benjamin's baptism in 2008—though neither veteran recognized the other nor knew of their shared history until Benjamin's discovery a decade later, which prompted an emotional family gathering where the two 93-year-old former adversaries embraced, shared their wartime experiences through translators, and marveled at how their bloodlines had ultimately converged in their great-grandson.",
    "extracted_information": {
        "discoverer_name": "Benjamin",
        "discoverer_relationship": "Son",
        "discovery_context": "Researching family tree for school project",
        "discovery_year": 2018,
        "paternal_ancestor": "William Harrison",
        "paternal_relationship": "Great-grandfather (husband's grandfather)",
        "paternal_military_role": "Bomber pilot in 8th Air Force during WWII",
        "paternal_aircraft": "B-17",
        "maternal_ancestor": "Rudolf Müller",
        "maternal_relationship": "Great-grandfather (my grandfather)",
        "maternal_military_circumstance": "Conscripted into Luftwaffe",
        "maternal_military_role": "Fighter pilot",
        "maternal_aircraft": "Messerschmitt",
        "historical_event": "Direct aerial combat",
        "combat_location": "Over Dresden",
        "combat_date": "February 15, 1945",
        "combat_documentation": "Military records and flight logs",
        "combat_outcome": "William's B-17 sustained damage, both men returned safely",
        "subsequent_meeting": "Benjamin's baptism",
        "meeting_year": 2008,
        "time_between_events": "60 years",
        "discovery_timing": "Decade after baptism",
        "response_to_discovery": "Emotional family gathering",
        "ancestors_ages": "93 years old",
        "ancestors_status": "Former adversaries",
        "interaction": "Embraced, shared wartime experiences through translators",
        "reflection": "Marveled at bloodlines converging in great-grandson"
    }
    },
    {
    "sentence": "My brother-in-law Jamal, an accomplished classical violinist who graduated from Juilliard in 2004 and performed with the Chicago Symphony Orchestra for eight years before an autoimmune disorder affecting his hands ended his performance career in 2013, underwent a remarkable personal transformation when he traveled to Mali to learn about his ancestral roots, discovered a natural affinity for traditional West African string instruments (particularly the kora and ngoni), studied under master musician Toumani Diabaté in Bamako for 18 months despite his ongoing physical limitations, married my sister-in-law Aminata (a linguistic anthropologist documenting endangered Mande languages) in a traditional ceremony in her home village in 2016, founded a music school for disadvantaged youth that has provided free instruction to over 400 children in both Western and African musical traditions, recorded a groundbreaking fusion album that won the World Music Grammy in 2020, and now divides his time between Chicago (where he teaches ethnomusicology at Northwestern) and Bamako (where he and Aminata are raising their three multilingual children – Malik, Nia, and little Ibrahim – who switch effortlessly between English, French, Bambara, and Arabic).",
    "extracted_information": {
        "name": "Jamal",
        "relationship": "Brother-in-law",
        "profession_1": "Classical violinist",
        "education": "Juilliard",
        "graduation_year": 2004,
        "employer": "Chicago Symphony Orchestra",
        "employment_duration": "Eight years",
        "career_ending_condition": "Autoimmune disorder affecting hands",
        "career_end_year": 2013,
        "transformative_journey": "Traveled to Mali to learn about ancestral roots",
        "musical_discovery": "Natural affinity for traditional West African string instruments",
        "specific_instruments": ["Kora", "Ngoni"],
        "mentor": "Toumani Diabaté",
        "training_location": "Bamako",
        "training_duration": "18 months",
        "training_challenge": "Ongoing physical limitations",
        "spouse_name": "Aminata",
        "spouse_relationship": "Sister-in-law",
        "spouse_profession": "Linguistic anthropologist",
        "spouse_work": "Documenting endangered Mande languages",
        "wedding_type": "Traditional ceremony",
        "wedding_location": "Her home village",
        "wedding_year": 2016,
        "foundation": "Music school for disadvantaged youth",
        "foundation_impact": "Free instruction to over 400 children",
        "teaching_curriculum": "Both Western and African musical traditions",
        "artistic_achievement": "Groundbreaking fusion album",
        "award": "World Music Grammy",
        "award_year": 2020,
        "current_residence_1": "Chicago",
        "current_occupation_1": "Teaches ethnomusicology at Northwestern",
        "current_residence_2": "Bamako",
        "children": ["Malik", "Nia", "Ibrahim"],
        "children_count": 3,
        "children_linguistic_ability": "Multilingual, switch between English, French, Bambara, and Arabic"
    }
    },
    {
    "sentence": "After being diagnosed with terminal pancreatic cancer in January 2021 and given only six months to live, my father—a reserved high school physics teacher who had never traveled outside North America—stunned our family by using his life savings and retirement fund to embark on what he called his 'farewell tour,' visiting all seven continents over the course of 14 months (including Antarctica on an icebreaker expedition and a safari in Tanzania where he tracked mountain gorillas), defying medical expectations through a combination of experimental immunotherapy treatments he received at various research hospitals during his travels, documenting his journey through daily video diaries that have accumulated over 3 million views on YouTube and inspired countless cancer patients to pursue their own bucket-list dreams, reconnecting with his estranged brother in Australia after a 35-year silence stemming from a business dispute in the 1980s, falling in love with and marrying a fellow cancer survivor (my now-stepmother Isabella) whom he met at a healing retreat in Bali, and miraculously entering complete remission in March 2023—a medical outcome so unexpected that his case is now being studied by oncologists at Mayo Clinic as part of research into spontaneous remissions correlated with major life changes.",
    "extracted_information": {
        "relationship": "Father",
        "medical_condition": "Terminal pancreatic cancer",
        "diagnosis_date": "January 2021",
        "prognosis": "Six months to live",
        "occupation": "High school physics teacher",
        "personality_trait": "Reserved",
        "previous_travel_limitation": "Never traveled outside North America",
        "financial_decision": "Used life savings and retirement fund",
        "journey_name": "Farewell tour",
        "travel_achievement": "Visiting all seven continents",
        "journey_duration": "14 months",
        "notable_destination_1": "Antarctica on icebreaker expedition",
        "notable_destination_2": "Safari in Tanzania tracking mountain gorillas",
        "medical_defiance": "Defying medical expectations",
        "treatment": "Experimental immunotherapy",
        "treatment_locations": "Various research hospitals during travels",
        "documentation_method": "Daily video diaries",
        "audience_reach": "Over 3 million views on YouTube",
        "impact": "Inspired countless cancer patients to pursue bucket-list dreams",
        "family_reconciliation": "Reconnected with estranged brother in Australia",
        "estrangement_duration": "35-year silence",
        "estrangement_cause": "Business dispute in the 1980s",
        "romantic_outcome": "Falling in love with and marrying fellow cancer survivor",
        "spouse_name": "Isabella",
        "spouse_relationship": "Now-stepmother",
        "meeting_context": "Healing retreat in Bali",
        "medical_outcome": "Complete remission",
        "remission_date": "March 2023",
        "medical_significance": "Case being studied by oncologists at Mayo Clinic",
        "research_context": "Research into spontaneous remissions correlated with major life changes"
    }
    },
    {
    "sentence": "After fleeing Cambodia in 1975 during the rise of the Khmer Rouge, my father-in-law Dr. Sovann Pheng—who had been the head of neurosurgery at Phnom Penh's Royal Hospital and whose parents and two youngest sisters perished in the killing fields—spent three years in a Thai refugee camp where he met my mother-in-law Chantrea (then working as a volunteer nurse), before they were granted asylum in France in 1978, eventually immigrating to Montreal in 1986 where he had to completely requalify as a doctor despite his extensive experience and credentials.",
    "extracted_information": {
        "name": "Sovann Pheng",
        "title": "Dr.",
        "relationship": "Father-in-law",
        "origin_country": "Cambodia",
        "emigration_year": 1975,
        "historical_context": "Rise of Khmer Rouge",
        "previous_occupation": "Head of neurosurgery",
        "previous_workplace": "Royal Hospital, Phnom Penh",
        "deceased_relatives": ["Parents", "Two youngest sisters"],
        "cause_of_relatives_death": "Killing fields",
        "interim_location": "Thai refugee camp",
        "interim_duration": "Three years",
        "spouse_name": "Chantrea",
        "spouse_occupation": "Volunteer nurse",
        "meeting_location": "Thai refugee camp",
        "asylum_country": "France",
        "asylum_year": 1978,
        "immigration_country": "Montreal",
        "immigration_year": 1986,
        "career_challenge": "Requalifying as doctor despite experience"
    }
    },
    {
    "sentence": "My paternal grandparents, Giuseppe and Maria Rossi, who were childhood sweethearts from the same small village in Tuscany, embarked on a grueling three-week journey across the Atlantic on the SS Augustus in April of 1937 with nothing but $27 in their pockets and Maria six months pregnant with my father, eventually settling in a predominantly Italian neighborhood in North Boston where Giuseppe worked three jobs simultaneously—as a cobbler during the day, a janitor in the evenings, and a baker in the early mornings—to save enough money to bring over his four younger brothers from Italy by 1948.",
    "extracted_information": {
        "name_1": "Giuseppe Rossi",
        "name_2": "Maria Rossi",
        "relationship": "Paternal grandparents",
        "relationship_status": "Childhood sweethearts",
        "origin": "Small village in Tuscany",
        "journey_duration": "Three weeks",
        "journey_mode": "Across Atlantic",
        "vessel_name": "SS Augustus",
        "journey_date": "April 1937",
        "financial_status": "$27",
        "pregnancy_status": "Six months pregnant",
        "unborn_child": "My father",
        "settlement_location": "Italian neighborhood in North Boston",
        "occupation_1": "Cobbler (day)",
        "occupation_2": "Janitor (evenings)",
        "occupation_3": "Baker (early mornings)",
        "financial_goal": "Bring four younger brothers from Italy",
        "goal_achievement_year": 1948
    }
    },
    {
    "sentence": "My eccentric uncle Lars Eriksson—my mother's older half-brother from her father's first marriage to a Swedish exchange student he met while studying abroad in Stockholm during the tumultuous winter of 1963—graduated with dual PhDs in quantum physics and medieval literature from MIT and Oxford respectively, before abandoning academia altogether in 1997 to live in a self-built treehouse in the remote forests of Oregon, where he has authored seventeen fantasy novels under the pseudonym 'L.E. Wolfmoon' and crafts intricate wooden puzzles that have been featured in the Museum of Modern Art's 2019 exhibition on unconventional craftsmanship.",
    "extracted_information": {
        "name": "Lars Eriksson",
        "relationship": "Uncle",
        "personality": "Eccentric",
        "family_connection": "Mother's older half-brother",
        "parent_relationship": "Father's first marriage",
        "parent_spouse_origin": "Swedish exchange student",
        "meeting_location": "Stockholm",
        "meeting_year": 1963    ,
        "meeting_season": "Winter",
        "meeting_context": "Studying abroad",
        "education_1": "PhD in quantum physics from MIT",
        "education_2": "PhD in medieval literature from Oxford",
        "career_change_year": 1997,
        "lifestyle_change": "Abandoned academia",
        "current_residence": "Self-built treehouse",
        "residence_location": "Remote forests of Oregon",
        "creative_output_1": "Seventeen fantasy novels",
        "pseudonym": "L.E. Wolfmoon",
        "creative_output_2": "Intricate wooden puzzles",
        "recognition": "Museum of Modern Art exhibition",
        "exhibition_year": 2019,
        "exhibition_theme": "Unconventional craftsmanship"
    }
    },
    {
    "sentence": "Despite growing up in rural poverty in Appalachia during the Great Depression and losing both his parents to a coal mining accident at the age of nine, my grandfather Thomas Jefferson Williams managed to secure a scholarship to Vanderbilt University in 1952 where he studied engineering on the GI Bill after serving as a radio operator in the Korean War, eventually going on to patent seventeen different hydraulic systems used in modern agriculture, all while raising my mother and her four siblings as a widower after my grandmother Eleanor succumbed to breast cancer in 1968 at the tragically young age of 37.",
    "extracted_information": {
        "name": "Thomas Jefferson Williams",
        "relationship": "Grandfather",
        "childhood_circumstances": "Rural poverty",
        "childhood_location": "Appalachia",
        "historical_context": "Great Depression",
        "parents_status": "Both deceased",
        "parents_cause_of_death": "Coal mining accident",
        "orphaned_age": 9,
        "education": "Vanderbilt University",
        "scholarship_year": 1952,
        "field_of_study": "Engineering",
        "funding_source": "GI Bill",
        "military_service": "Radio operator in Korean War",
        "achievements": "Patented seventeen hydraulic systems",
        "innovation_field": "Modern agriculture",
        "parental_status": "Widower",
        "spouse_name": "Eleanor",
        "spouse_cause_of_death": "Breast cancer",
        "spouse_death_year": 1968,
        "spouse_age_at_death": 37,
        "children": "Mother and four siblings",
        "number_of_children": 5
    }
    },
    {
    "sentence": "My wife's sister, Commander Sophia Chen-Williams, who graduated top of her class at Annapolis in 2005, has served on three different nuclear submarines—the USS Ohio, USS Michigan, and USS Florida—during her distinguished 20-year naval career, earning the Navy Cross for her actions during a classified operation in the South China Sea in 2017, while simultaneously raising three children with her wife Jennifer (a civilian marine biologist) and completing a master's degree in nuclear engineering through a special Navy program, all while raising her twin daughters Maya and Lily (born through IVF with donor sperm after her wife Jessica was diagnosed with ovarian cancer in 2012) and completing a master's degree in international relations from Georgetown through their distance learning program.",
    "extracted_information": {
        "name": "Sophia Chen-Williams",
        "military_rank": "Commander",
        "relationship": "Wife's sister",
        "education": "Annapolis",
        "graduation_year": 2005,
        "graduation_achievement": "Top of class",
        "service_vessels": ["USS Ohio", "USS Michigan", "USS Florida"],
        "vessel_type": "Nuclear submarines",
        "career_duration": "20-year naval career",
        "award": "Navy Cross",
        "award_reason": "Actions during classified operation",
        "operation_location": "South China Sea",
        "operation_year": 2017,
        "spouse_name": "Jennifer",
        "spouse_occupation": "Civilian marine biologist",
        "children_count": 3,
        "additional_education": "Master's degree in nuclear engineering",
        "education_context": "Special Navy program",
        "children": "Twin daughters Maya and Lily",
        "children_birth_method": "IVF with donor sperm",
        "spouse_medical_condition": "Ovarian cancer",
        "spouse_diagnosis_year": 2012,
        "additional_education_2": "Master's degree in international relations",
        "education_institution_2": "Georgetown",
        "education_method": "Distance learning program"
    }
    },      
    {
    "sentence": "Having survived both the Armenian genocide as a child in 1915—during which she witnessed the murder of her parents and three older brothers before being rescued by a Kurdish family who hid her in their cellar for eighteen months—and later the bombing of Dresden in February 1945 while working as a nurse for the Red Cross, my husband's grandmother Tamar Hagopian-Schmidt immigrated to the United States in 1952 via the Displaced Persons Act, bringing with her only a small silver cross that had belonged to her mother and an illustrated manuscript of Armenian folk tales that she had painstakingly recreated from memory while recovering from tuberculosis in a Swiss sanatorium between 1947 and 1949.",
    "extracted_information": {
        "name": "Tamar Hagopian-Schmidt",
        "relationship": "Husband's grandmother",
        "survival_event_1": "Armenian genocide",
        "survival_event_1_year": 1915,
        "survival_event_1_age": "Child",
        "witnessed_deaths": ["Parents", "Three older brothers"],
        "rescuers": "Kurdish family",
        "hiding_location": "Cellar",
        "hiding_duration": "Eighteen months",
        "survival_event_2": "Bombing of Dresden",
        "survival_event_2_date": "February 1945",
        "occupation_during_event_2": "Nurse",
        "employer": "Red Cross",
        "immigration_year": 1952,
        "immigration_destination": "United States",
        "immigration_method": "Displaced Persons Act",
        "possession_1": "Small silver cross",
        "possession_1_origin": "Belonged to her mother",
        "possession_2": "Illustrated manuscript of Armenian folk tales",
        "possession_2_origin": "Recreated from memory",
        "medical_condition": "Tuberculosis",
        "recovery_location": "Swiss sanatorium",
        "recovery_period": "1947-1949"
    }
    },
    {
    "sentence": "My youngest daughter's godfather, Dr. Isaiah Washington, who was raised by his grandmother in the South Side of Chicago after his father was incarcerated for a crime he didn't commit and his mother succumbed to drug addiction brought on by grief and poverty, defied all statistical odds by securing a full scholarship to Johns Hopkins at seventeen, becoming the youngest neurosurgeon in the hospital's history at twenty-nine, pioneering a revolutionary technique for pediatric brain tumor removal that reduced mortality rates by 63% between 2012 and 2019, adopting three children from the foster care system with his husband Miguel, and establishing a foundation that has provided over $5 million in medical school scholarships for underprivileged youth from inner-city communities.",
    "extracted_information": {
        "name": "Isaiah Washington",
        "title": "Dr.",
        "relationship": "Youngest daughter's godfather",
        "raised_by": "Grandmother",
        "childhood_location": "South Side of Chicago",
        "father_status": "Incarcerated for crime he didn't commit",
        "mother_status": "Succumbed to drug addiction",
        "mother_circumstances": "Grief and poverty",
        "achievement_context": "Defied statistical odds",
        "education": "Johns Hopkins",
        "scholarship_type": "Full scholarship",
        "scholarship_age": 17,
        "career": "Neurosurgeon",
        "career_achievement": "Youngest neurosurgeon in hospital's history",
        "achievement_age": 29,
        "medical_innovation": "Revolutionary technique for pediatric brain tumor removal",
        "innovation_impact": "Reduced mortality rates by 63%",
        "innovation_period": "2012-2019",
        "children_status": "Adopted three children from foster care system",
        "number_of_children": 3,
        "spouse_name": "Miguel",
        "foundation_achievement": "Provided over $5 million in medical school scholarships",
        "foundation_beneficiaries": "Underprivileged youth from inner-city communities"
    }
    },
    {
    "sentence": "When my maternal great-uncle Mohandas 'Mo' Patel—who famously renounced his inheritance as the heir to a textile empire in Mumbai to become a civil rights attorney in Mississippi during the turbulent 1960s, was photographed alongside Martin Luther King Jr. during the march from Selma to Montgomery in 1965, survived three separate assassination attempts by white supremacists between 1968 and 1972, and later served as a federal judge after being appointed by President Carter in 1979—passed away peacefully in his sleep on December 18, 2020, at the age of 96, his memorial service was attended virtually by over 7,000 people from 43 different countries, including three former U.S. presidents and dozens of civil rights leaders whose cases he had supported pro bono throughout his long and distinguished career.",
    "extracted_information": {
        "name": "Mohandas 'Mo' Patel",
        "relationship": "Maternal great-uncle",
        "renounced_status": "Heir to textile empire",
        "origin_location": "Mumbai",
        "career_choice": "Civil rights attorney",
        "career_location": "Mississippi",
        "historical_period": "Turbulent 1960s",
        "historical_event": "March from Selma to Montgomery",
        "historical_figure_association": "Martin Luther King Jr.",
        "event_year": 1965,
        "survival_events": "Three separate assassination attempts",
        "survival_period": "1968-1972",
        "attackers": "White supremacists",
        "later_position": "Federal judge",
        "appointment": "By President Carter",
        "appointment_year": 1979,
        "death_date": "December 18, 2020",
        "death_manner": "Peacefully in his sleep",
        "age_at_death": 96,
        "memorial_attendees_count": "Over 7,000 people",
        "memorial_countries_represented": 43,
        "notable_attendees": "Three former U.S. presidents and dozens of civil rights leaders",
        "pro_bono_work": "Supported civil rights cases"
    }
    },
    {
    "sentence": "Though initially mistaken as fraternal due to their noticeably different complexions—with Emily having inherited our father's pale Irish skin and auburn hair while Madison takes after our mother's Nigerian-Brazilian heritage with deep brown skin and tightly coiled black hair—my twelve-year-old twin sisters, who were born eight weeks premature on Leap Day 2012 at Brigham and Women's Hospital in Boston weighing only 3 pounds each and spent their first month in the NICU before finally coming home, are actually identical twins according to genetic testing conducted as part of a fascinating Harvard Medical School study on epigenetic factors that can cause identical twins to present with different phenotypic expressions, particularly in mixed-race families.",
    "extracted_information": {
        "name_1": "Emily",
        "name_2": "Madison",
        "relationship": "Twin sisters",
        "age": "Twelve years old",
        "twin_type_appearance": "Fraternal",
        "twin_type_genetic": "Identical",
        "physical_traits_1": "Pale Irish skin and auburn hair",
        "physical_traits_2": "Deep brown skin and tightly coiled black hair",
        "heritage_1": "Father's Irish",
        "heritage_2": "Mother's Nigerian-Brazilian",
        "birth_circumstances": "Eight weeks premature",
        "birth_date": "Leap Day 2012",
        "birth_location": "Brigham and Women's Hospital, Boston",
        "birth_weight": "3 pounds each",
        "postnatal_care": "NICU",
        "postnatal_care_duration": "One month",
        "genetic_study": "Harvard Medical School study",
        "study_focus": "Epigenetic factors causing different phenotypic expressions",
        "study_context": "Mixed-race families"
    }
    },
    {
    "sentence": "My cousin Alexander—whose father (my mother's brother Robert) disappeared while on a solo sailing expedition in the Bermuda Triangle in 1998, prompting my aunt Victoria to relocate from their home in Nova Scotia to our family compound in rural Vermont where she raised Alexander and his younger sister Elizabeth with the help of our extended family—shocked everyone at Thanksgiving dinner in 2018 by announcing that he had conducted a private investigation over the course of three years and discovered that his father had not perished at sea as presumed but had secretly established a new identity as 'Richard Miller' and started a second family in New Zealand, a revelation that led to a contentious legal battle over my grandfather's estate that continues to divide our once close-knit family to this day.",
    "extracted_information": {
        "name_1": "Alexander",
        "relationship_1": "Cousin",
        "father_name": "Robert",
        "father_relationship": "Mother's brother",
        "father_disappearance": "Solo sailing expedition in Bermuda Triangle",
        "disappearance_year": 1998,
        "mother_name": "Victoria",
        "mother_relationship": "Aunt",
        "original_residence": "Nova Scotia",
        "relocation_destination": "Family compound in rural Vermont",
        "sibling_name": "Elizabeth",
        "sibling_relationship": "Younger sister",
        "support_system": "Extended family",
        "revelation_event": "Thanksgiving dinner",
        "revelation_year": 2018,
        "investigation_duration": "Three years",
        "investigation_finding": "Father established new identity",
        "father_new_identity": "Richard Miller",
        "father_new_location": "New Zealand",
        "father_new_circumstance": "Started second family",
        "consequence": "Contentious legal battle",
        "disputed_property": "Grandfather's estate",
        "family_impact": "Division of once close-knit family",
        "ongoing_status": "Continues to this day"
    }
    },
    {
    "sentence": "After being diagnosed with a rare form of early-onset Alzheimer's at the unusually young age of 48 in 2015, my mother—an accomplished concert pianist who had performed with major symphonies on four continents and taught at Juilliard for nearly two decades—embarked on an ambitious project to record all of Chopin's 21 Nocturnes in a race against her declining cognitive abilities, completing the final recording just three days before she could no longer remember how to play the piano, leaving behind this remarkable musical legacy for her seven grandchildren (including my twins Sophia and Noah, who have both inherited her perfect pitch) along with a series of video diaries documenting her experience with the disease that have since been incorporated into a groundbreaking neurological study at Columbia University on the relationship between musical memory and cognitive decline.",
    "extracted_information": {
        "relationship": "Mother",
        "medical_condition": "Rare form of early-onset Alzheimer's",
        "diagnosis_age": 48,
        "diagnosis_year": 2015,
        "profession": "Concert pianist",
        "professional_achievement_1": "Performed with major symphonies on four continents",
        "professional_achievement_2": "Taught at Juilliard",
        "teaching_duration": "Nearly two decades",
        "final_project": "Recording all of Chopin's 21 Nocturnes",
        "project_motivation": "Race against declining cognitive abilities",
        "project_completion_timing": "Three days before could no longer remember how to play",
        "legacy_recipients": "Seven grandchildren",
        "named_grandchildren": ["Sophia", "Noah"],
        "grandchildren_relationship": "Twins",
        "inherited_trait": "Perfect pitch",
        "additional_legacy": "Video diaries documenting experience with disease",
        "research_contribution": "Incorporated into neurological study",
        "research_institution": "Columbia University",
        "research_focus": "Relationship between musical memory and cognitive decline"
    }
    },
    {
    "sentence": "My husband's aunt, Dr. Fatima Al-Zahrani, a renowned archaeologist specializing in pre-Islamic Arabian settlements who discovered the previously unknown trading outpost of Wahat al-Qirwan in the Empty Quarter of Saudi Arabia in 2004 (a find that completely revised scholarly understanding of ancient trade routes across the Arabian Peninsula), was tragically killed alongside her wife Rachel and their adopted son Tariq in the 2015 terrorist bombing of the National Museum in Tunis where she had been invited as a visiting curator for an exhibition on cultural exchanges between North Africa and the Arabian Peninsula during the 3rd century BCE, leaving behind a monumental 1,200-page manuscript that my husband has spent the last seven years editing and preparing for publication by Oxford University Press in 2023.",
    "extracted_information": {
        "name": "Dr. Fatima Al-Zahrani",
        "title": "Dr.",
        "relationship": "Husband's aunt",
        "profession": "Archaeologist",
        "specialization": "Pre-Islamic Arabian settlements",
        "discovery": "Trading outpost of Wahat al-Qirwan",
        "discovery_location": "Empty Quarter of Saudi Arabia",
        "discovery_year": 2004,
        "discovery_significance": "Revised understanding of ancient trade routes across Arabian Peninsula",
        "death_circumstance": "Terrorist bombing",
        "death_location": "National Museum in Tunis",
        "death_year": 2015,
        "spouse_name": "Rachel",
        "spouse_status": "Deceased in same bombing",
        "child_name": "Tariq",
        "child_status": "Adopted son, deceased in same bombing",
        "professional_role": "Visiting curator",
        "exhibition_topic": "Cultural exchanges between North Africa and Arabian Peninsula during 3rd century BCE",
        "posthumous_work": "1,200-page manuscript",
        "editor": "Husband",
        "editing_duration": "Seven years",
        "publication_entity": "Oxford University Press",
        "publication_year": 2023
    }
    },
    {
    "sentence": "Born into a prominent Brahmin family in Kerala, my father-in-law Vikram abandoned his predetermined path to priesthood at the age of 16 to join Mahatma Gandhi's Salt March in 1930, was subsequently imprisoned by British colonial authorities for three years, completed his education at the University of Calcutta after his release, joined the Indian independence movement alongside Nehru, witnessed the Partition of India from his posting as a civil servant in Delhi in 1947, emigrated to Canada in 1968 with his wife Lakshmi and their four children (including my wife Priya) after being disillusioned by religious sectarianism, established the first South Asian cultural center in Vancouver in 1973, and at the remarkable age of 106, continues to give weekly lectures via Zoom on the history of India's independence movement to university students across North America.",
    "extracted_information": {
        "relationship": "Father-in-law",
        "name": "Vikram",
        "birth_status": "Born into prominent Brahmin family",
        "birth_location": "Kerala",
        "abandoned_path": "Predetermined path to priesthood",
        "decision_age": 16,
        "historical_event_1": "Joined Mahatma Gandhi's Salt March",
        "event_1_year": 1930,
        "consequence": "Imprisoned by British colonial authorities",
        "imprisonment_duration": "Three years",
        "education": "University of Calcutta",
        "political_involvement": "Indian independence movement",
        "political_association": "Alongside Nehru",
        "historical_event_2": "Witnessed Partition of India",
        "professional_role": "Civil servant",
        "location_during_event_2": "Delhi",
        "event_2_year": 1947,
        "emigration_year": 1968,
        "emigration_destination": "Canada",
        "emigration_reason": "Disillusioned by religious sectarianism",
        "spouse_name": "Lakshmi",
        "children_count": 4,
        "named_child": "Priya",
        "named_child_relationship": "Wife",
        "achievement": "Established first South Asian cultural center in Vancouver",
        "achievement_year": 1973,
        "current_age": 106,
        "current_activity": "Weekly lectures via Zoom",
        "lecture_topic": "History of India's independence movement",
        "audience": "University students across North America"
    }
    },
    {
    "sentence": "Despite losing both of her legs below the knee in a horrific car accident caused by a drunk driver on her way home from her high school graduation in June 2015, my younger sister Eleanor—who spent eight months in intensive physical rehabilitation at the Shirley Ryan AbilityLab in Chicago learning to walk with prosthetic limbs before enrolling at MIT on a full academic scholarship she had been awarded prior to the accident—went on to become a Paralympic swimming gold medalist representing the United States in Tokyo in 2021, founded a nonprofit organization called 'Limitless' that has provided customized athletic prosthetics to over 500 children from disadvantaged backgrounds, completed her Ph.D. in biomedical engineering with a focus on next-generation prosthetic technologies at the age of 25, and recently accepted a prestigious position at DARPA overseeing a $40 million research initiative to develop neural-integrated adaptive prosthetics for military veterans.",
    "extracted_information": {
        "name": "Eleanor",
        "relationship": "Younger sister",
        "injury": "Lost both legs below the knee",
        "injury_cause": "Car accident caused by drunk driver",
        "injury_context": "On way home from high school graduation",
        "injury_date": "June 2015",
        "rehabilitation_duration": "Eight months",
        "rehabilitation_type": "Intensive physical rehabilitation",
        "rehabilitation_location": "Shirley Ryan AbilityLab, Chicago",
        "rehabilitation_focus": "Learning to walk with prosthetic limbs",
        "education_institution": "MIT",
        "scholarship_type": "Full academic scholarship",
        "scholarship_timing": "Awarded prior to accident",
        "athletic_achievement": "Paralympic swimming gold medalist",
        "athletic_representation": "United States",
        "athletic_event_location": "Tokyo",
        "athletic_event_year": 2021,
        "organization_founded": "Limitless",
        "organization_purpose": "Provided customized athletic prosthetics",
        "beneficiaries_count": "Over 500 children",
        "beneficiaries_background": "Disadvantaged backgrounds",
        "advanced_degree": "Ph.D. in biomedical engineering",
        "research_focus": "Next-generation prosthetic technologies",
        "completion_age": 25,
        "current_position": "Position at DARPA",
        "project_budget": "$40 million",
        "project_focus": "Neural-integrated adaptive prosthetics",
        "project_beneficiaries": "Military veterans"
    }
    },
    {
    "sentence": "My grandfather on my father's side, Reverend Elijah Jefferson Montgomery III, who was born in rural Mississippi to sharecroppers in 1932, became the first person in his family to attend college after being secretly taught to read by the daughter of the plantation owner, earned his divinity degree from Howard University in 1958, marched alongside Martin Luther King Jr. in Washington in 1963, pastored the same church in Memphis for 42 years while raising eight children (including my father) after my grandmother Josephine died during childbirth with their youngest son in 1970, received the Presidential Medal of Freedom in 2012 for his lifetime of civil rights activism, and recently celebrated his 93rd birthday by skydiving for the first time—a lifelong dream he had postponed until all of his 27 grandchildren and 14 great-grandchildren could attend the event together.",
    "extracted_information": {
        "name": "Elijah Jefferson Montgomery III",
        "title": "Reverend",
        "relationship": "Grandfather on father's side",
        "birth_location": "Rural Mississippi",
        "birth_year": 1932,
        "parents_occupation": "Sharecroppers",
        "educational_milestone": "First person in family to attend college",
        "learning_circumstance": "Secretly taught to read",
        "teacher": "Daughter of plantation owner",
        "degree": "Divinity degree",
        "alma_mater": "Howard University",
        "graduation_year": 1958,
        "historical_event": "Marched alongside Martin Luther King Jr. in Washington",
        "historical_event_year": 1963,
        "profession": "Pastor",
        "workplace_location": "Memphis",
        "career_duration": "42 years",
        "children_count": 8,
        "named_child": "Father",
        "spouse_name": "Josephine",
        "spouse_death_circumstance": "Died during childbirth",
        "spouse_death_year": 1970,
        "death_relation": "Youngest son",
        "honor_received": "Presidential Medal of Freedom",
        "honor_year": 2012,
        "honor_reason": "Lifetime of civil rights activism",
        "current_age": 93,
        "recent_achievement": "Skydiving for the first time",
        "achievement_description": "Lifelong dream",
        "achievement_attendance": "All 27 grandchildren and 14 great-grandchildren",
        "grandchildren_count": 27,
        "great-grandchildren_count": 14
    }
    }
]}

